[
  {
    "id": 1,
    "username": "hb100",
    "password": "123b123",
    "phone": "0978567209",
    "email": "muahakhongcoem@proton.em",
    "createdAt": "2026-06-07T05:40:38.144Z",
    "banned": false,
    "banType": null,
    "banMessage": null,
    "banExpiresAt": null,
    "bannedAt": null,
    "wrongAttempts": 0,
    "lockCount": 0
  },
  {
    "id": 2,
    "username": "testuser2145106967",
    "password": "pass123",
    "phone": "",
    "email": "user2145106967@test.com",
    "createdAt": "2026-06-07T05:42:35.402Z",
    "banned": false,
    "banType": null,
    "banMessage": null,
    "banExpiresAt": null,
    "bannedAt": null
  },
  {
    "id": 3,
    "username": "hb789",
    "password": "00abc00",
    "phone": "0978567999",
    "email": "muahakhongcoem@proton.net",
    "createdAt": "2026-06-07T06:29:49.530Z",
    "banned": false,
    "banType": null,
    "banMessage": null,
    "banExpiresAt": null,
    "bannedAt": null,
    "wrongAttempts": 0,
    "lockCount": 0
  },
  {
    "id": 4,
    "username": "dg123",
    "password": "123a123",
    "phone": "9999181811",
    "email": "fudokeva@denipl.com",
    "createdAt": "2026-06-07T06:35:45.683Z",
    "banned": false,
    "banType": null,
    "banMessage": null,
    "banExpiresAt": null,
    "bannedAt": null,
    "wrongAttempts": 0,
    "lockCount": 0
  },
  {
    "id": 5,
    "username": "k123",
    "password": "123qqq",
    "phone": "991876262",
    "email": "muahakhongcoem@proton.poppp",
    "createdAt": "2026-06-07T07:04:56.744Z",
    "banned": false,
    "banType": null,
    "banMessage": null,
    "banExpiresAt": null,
    "bannedAt": null
  },
  {
    "id": 6,
    "username": "chi11",
    "password": "123chi456",
    "phone": "6543331331",
    "email": "chi@a.b.c",
    "createdAt": "2026-06-07T07:27:13.062Z",
    "banned": false,
    "banType": null,
    "banMessage": null,
    "banExpiresAt": null,
    "bannedAt": null,
    "wrongAttempts": 0,
    "lockCount": 0
  },
  {
    "id": 7,
    "username": "ngoc1991",
    "password": "ngoc12345",
    "phone": "0976551222",
    "email": "ngoc@vn.com",
    "createdAt": "2026-06-08T02:47:10.545Z",
    "banned": true,
    "banType": "ban",
    "banMessage": "Thông tin cá nhân giả mạo",
    "banExpiresAt": 1781161211423,
    "bannedAt": 1780902011423,
    "membershipType": "Thường",
    "membershipPlan": null,
    "membershipPlanName": null,
    "membershipStartDate": null,
    "membershipEndDate": null,
    "membershipDiscount": 0,
    "membershipFreeShipping": 0,
    "banReason": "Thông tin cá nhân giả mạo"
  },
  {
    "id": 8,
    "username": "chin966",
    "password": "chin123",
    "phone": "1234567",
    "email": "96game@vn.net",
    "createdAt": "2026-06-08T07:12:18.083Z",
    "banned": false,
    "banType": null,
    "banMessage": null,
    "banExpiresAt": null,
    "bannedAt": null,
    "membershipType": "Thường",
    "membershipPlan": null,
    "membershipPlanName": null,
    "membershipStartDate": null,
    "membershipEndDate": null,
    "membershipDiscount": 0,
    "membershipFreeShipping": 0
  }
]